fulcrum_ai/__init__.py
fulcrum_ai/client.py
fulcrum_ai/modules/__init__.py
fulcrum_ai/modules/config/__init__.py
fulcrum_ai/modules/config/constants.py
fulcrum_ai/modules/config/env.py
fulcrum_ai/modules/interfaces/__init__.py
fulcrum_ai/modules/interfaces/endpoints/__init__.py
fulcrum_ai/modules/interfaces/endpoints/projects/__init__.py
fulcrum_ai/modules/interfaces/endpoints/projects/prompts/__init__.py
fulcrum_ai/modules/interfaces/endpoints/projects/prompts/get.py
fulcrum_ai/modules/interfaces/endpoints/projects/prompts/logs/__init__.py
fulcrum_ai/modules/interfaces/endpoints/projects/prompts/logs/create.py
fulcrum_ai/modules/interfaces/endpoints/projects/prompts/logs/update.py
fulcrum_ai/modules/interfaces/endpoints/types/__init__.py
fulcrum_ai/modules/interfaces/endpoints/types/projects/__init__.py
fulcrum_ai/modules/interfaces/endpoints/types/projects/prompts/__init__.py
fulcrum_ai/modules/interfaces/endpoints/types/projects/prompts/logs/__init__.py
fulcrum_ai/modules/interfaces/endpoints/types/projects/prompts/logs/messages/__init__.py
fulcrum_ai/modules/interfaces/endpoints/types/projects/prompts/logs/messages/content_types.py
fulcrum_ai/modules/interfaces/endpoints/types/projects/prompts/logs/messages/messages.py
fulcrum_ai/modules/interfaces/endpoints/types/projects/prompts/logs/token_details/__init__.py
fulcrum_ai/modules/interfaces/endpoints/types/projects/prompts/logs/token_details/input_tokens.py
fulcrum_ai/modules/interfaces/endpoints/types/projects/prompts/logs/token_details/output_tokens.py
fulcrum_ai/modules/interfaces/endpoints/types/projects/prompts/logs/token_details/token_details.py
fulcrum_ai/modules/interfaces/endpoints/types/projects/prompts/prompt_settings/__init__.py
fulcrum_ai/modules/interfaces/endpoints/types/projects/prompts/prompt_settings/prompt_settings.py
fulcrum_ai/modules/interfaces/types/__init__.py
fulcrum_ai/projects/__init__.py
fulcrum_ai/projects/prompts/__init__.py
fulcrum_ai/projects/prompts/client.py
fulcrum_ai-0.0.1.dist-info/METADATA
fulcrum_ai-0.0.1.dist-info/WHEEL
fulcrum_ai-0.0.1.dist-info/top_level.txt
fulcrum_ai-0.0.1.dist-info/RECORD
