Metadata-Version: 2.4
Name: fulcrum-ai
Version: 0.0.1
Summary: Public pythonsdk for Fulcrum AI.
Author: Darren Jackson
Classifier: Programming Language :: Python :: 3
Classifier: Operating System :: OS Independent
Requires-Python: >=3.10
Requires-Dist: aiohappyeyeballs==2.6.1
Requires-Dist: aiohttp==3.12.15
Requires-Dist: aiosignal==1.4.0
Requires-Dist: annotated-types==0.7.0
Requires-Dist: attrs==25.3.0
Requires-Dist: certifi==2025.8.3
Requires-Dist: charset-normalizer==3.4.3
Requires-Dist: frozenlist==1.7.0
Requires-Dist: idna==3.10
Requires-Dist: multidict==6.6.4
Requires-Dist: propcache==0.3.2
Requires-Dist: pydantic==2.11.7
Requires-Dist: pydantic_core==2.33.2
Requires-Dist: python-decouple==3.8
Requires-Dist: requests==2.32.5
Requires-Dist: typing-inspection==0.4.1
Requires-Dist: typing_extensions==4.14.1
Requires-Dist: urllib3==2.5.0
Requires-Dist: yarl==1.20.1
Dynamic: author
Dynamic: classifier
Dynamic: description
Dynamic: description-content-type
Dynamic: requires-dist
Dynamic: requires-python
Dynamic: summary
